{
  "vstName": "PolyComp",
  "parameters": [
    {
      "name": "HQ",
      "type": "button"
    },
    {
      "name": "Power",
      "type": "button"
    },
    {
      "name": "RMS",
      "type": "button"
    },
    {
      "name": "Low Crossover",
      "type": "knob"
    },
    {
      "name": "High Crossover",
      "type": "knob"
    },
    {
      "name": "Low Threshold",
      "type": "knob"
    },
    {
      "name": "Low Ratio",
      "type": "knob"
    },
    {
      "name": "Low Attack",
      "type": "knob"
    },
    {
      "name": "Low Release",
      "type": "knob"
    },
    {
      "name": "Low Gain",
      "type": "knob"
    },
    {
      "name": "Low Switch",
      "type": "indent"
    },
    {
      "name": "Mid Threshold",
      "type": "knob"
    },
    {
      "name": "Mid Ratio",
      "type": "knob"
    },
    {
      "name": "Mid Attack",
      "type": "knob"
    },
    {
      "name": "Mid Release",
      "type": "knob"
    },
    {
      "name": "Mid Gain",
      "type": "knob"
    },
    {
      "name": "Mid Switch",
      "type": "indent"
    },
    {
      "name": "High Threshold",
      "type": "knob"
    },
    {
      "name": "High Ratio",
      "type": "knob"
    },
    {
      "name": "High Attack",
      "type": "knob"
    },
    {
      "name": "High Release",
      "type": "knob"
    },
    {
      "name": "High Gain",
      "type": "knob"
    },
    {
      "name": "High Switch",
      "type": "indent"
    },
    {
      "name": "Mix",
      "type": "knob"
    },
    {
      "name": "Input Gain",
      "type": "knob"
    },
    {
      "name": "Output Gain",
      "type": "knob"
    },
    {
      "name": "Sidechain",
      "type": "button"
    },
    {
      "name": "Bypass",
      "type": ""
    },
    {
      "name": "Bypass",
      "type": ""
    },
    {
      "name": "Wet",
      "type": ""
    },
    {
      "name": "Delta",
      "type": ""
    }
  ],
  "type": "dyn"
}